{
  "Water": "fluid:water",
  "Shield": "minecraft:shield:0",
  "Potion of Strength": "minecraft:potion:0:e37bb761",
  "Knightslime Tough Tool Rod": "tconstruct:tough_tool_rod:0:eb40d90c",
  "Iron Pan": "tconstruct:pan_head:0:fdacad4d",
  "Obsidian Axe Head": "tconstruct:axe_head:0:4df63d20",
  "Node Router": "bloodmagic:ItemNodeRouter:0",
  "Casting Table": "tconstruct:casting:0",
  "String": "minecraft:string:0",
  "Diamond Helmet": "minecraft:diamond_helmet:0",
  "Molten Iron": "fluid:iron",
  "Clock": "minecraft:clock:0",
  "Apprentice Blood Orb": "bloodmagic:ItemBloodOrb:1",
  "Green Slimy Mud": "tconstruct:soil:1",
  "Mossy Stone Bricks": "minecraft:stonebrick:1",
  "Saturation Module": "rftools:saturation_module:0",
  "Compression Reagent": "bloodmagic:ItemComponent:14",
  "Knightslime Shovel Head": "tconstruct:shovel_head:0:eb40d90c",
  "Pillar Quartz Block": "minecraft:quartz_block:2",
  "Paper Binding": "tconstruct:binding:0:d3d5a7d",
  "Bowl": "minecraft:bowl:0",
  "Firewood Sign Plate": "tconstruct:sign_head:0:aa8d0aa8",
  "Lingering Potion of Night Vision": "minecraft:lingering_potion:0:c25fe7cd",
  "Milk": "minecraft:milk_bucket:0",
  "Tiled Obsidian Path": "bloodmagic:BlockPath:7",
  "Arrow": "minecraft:arrow:0",
  "Acacia Wood Stairs": "minecraft:acacia_stairs:0",
  "Jungle Wood": "minecraft:log:3",
  "Nether Brick Slab": "minecraft:stone_slab:6",
  "Fire Charge": "minecraft:fire_charge:0",
  "Seared Road": "tconstruct:seared:7",
  "Daylight Sensor": "minecraft:daylight_detector:0",
  "Furnace": "minecraft:furnace:0",
  "End Tough Tool Rod": "tconstruct:tough_tool_rod:0:ccc1936f",
  "Excavator Head Cast": "tconstruct:cast:0:2c79a446",
  "Blue Orchid": "minecraft:red_flower:1",
  "Arrow of Slowness": "minecraft:tipped_arrow:0:fe290b73",
  "Arrow of Invisibility": "minecraft:tipped_arrow:0:1ba7f9d2",
  "White Stained Glass": "minecraft:stained_glass:0",
  "Splash Potion of Poison": "minecraft:splash_potion:0:4b7d2da8",
  "Slime Pan": "tconstruct:pan_head:0:1424241f",
  "Pink Tulip": "minecraft:red_flower:7",
  "Golden Shovel": "minecraft:golden_shovel:0",
  "Frame Parts": "bloodmagic:ItemComponent:10",
  "Endergenic Generator": "rftools:endergenic:0",
  "Wooden Tough Tool Rod": "tconstruct:tough_tool_rod:0:156619f2",
  "Redstone Receiver": "rftools:redstone_receiver_block:0",
  "Paper Sword Blade": "tconstruct:sword_blade:0:d3d5a7d",
  "Lingering Potion of Swiftness": "minecraft:lingering_potion:0:328e8805",
  "Seared Paver": "tconstruct:seared:2",
  "Enhanced Teleposition Focus": "bloodmagic:ItemTelepositionFocus:1",
  "Storage Filter Module": "rftools:filter_module:0",
  "Obsidian Shovel Head": "tconstruct:shovel_head:0:4df63d20",
  "Sugar Canes": "minecraft:reeds:0",
  "Ritual Stone of Dawn": "bloodmagic:BlockRitualStone:6",
  "Mud Bricks": "tconstruct:soil:6",
  "Purple Slime Sapling": "tconstruct:slime_sapling:1",
  "Hand Guard Cast": "tconstruct:cast:0:d0c773d7",
  "Bone Tool Rod": "tconstruct:tool_rod:0:f18fe449",
  "Rabbit Hide": "minecraft:rabbit_hide:0",
  "Block Protector": "rftools:block_protector:0",
  "Pickaxe Head Clay Cast": "tconstruct:clay_cast:0:97ab71d2",
  "Lingering Potion of Harming": "minecraft:lingering_potion:0:997f14a6",
  "Sigil of Magnetism": "bloodmagic:ItemSigilMagnetism:0",
  "Purple Stained Glass": "minecraft:stained_glass:10",
  "Fishing Rod": "minecraft:fishing_rod:0",
  "Prismarine": "minecraft:prismarine:0",
  "Slime Tough Tool Rod": "tconstruct:tough_tool_rod:0:1424241f",
  "Ardite Tough Tool Rod": "tconstruct:tough_tool_rod:0:f34653ac",
  "Lava Sigil": "bloodmagic:ItemSigilLava:0",
  "Arrow of Leaping": "minecraft:tipped_arrow:0:bea1eb2",
  "Dark Oak Wood Slab": "minecraft:wooden_slab:5",
  "Shears": "minecraft:shears:0",
  "Feather": "minecraft:feather:0",
  "Jungle Wood Slab": "minecraft:wooden_slab:3",
  "Cobalt Wide Guard": "tconstruct:wide_guard:0:207823b8",
  "Elemental Inscription Tool: Fire": "bloodmagic:ItemInscriptionTool:2",
  "Spruce Fence": "minecraft:spruce_fence:0",
  "Phantom Bridge Reagent": "bloodmagic:ItemComponent:15",
  "Diamond Chestplate": "minecraft:diamond_chestplate:0",
  "Cobalt Axe Head": "tconstruct:axe_head:0:207823b8",
  "Tough Tool Rod Clay Cast": "tconstruct:clay_cast:0:87e83866",
  "Demonic Will": "bloodmagic:ItemMonsterSoul:0",
  "Lapis Lazuli": "minecraft:dye:4",
  "Firewood Pan": "tconstruct:pan_head:0:aa8d0aa8",
  "Stone Hammer Head": "tconstruct:hammer_head:0:cc51ef16",
  "Ardite Large Sword Blade": "tconstruct:large_sword_blade:0:f34653ac",
  "Bone Pan": "tconstruct:pan_head:0:f18fe449",
  "Iron Shovel Head": "tconstruct:shovel_head:0:fdacad4d",
  "Flint and Steel": "minecraft:flint_and_steel:0",
  "Obsidian Binding": "tconstruct:binding:0:4df63d20",
  "Modular Storage": "rftools:modular_storage:0",
  "Cooked Porkchop": "minecraft:cooked_porkchop:0",
  "Shard Cast": "tconstruct:cast:0:4802caf2",
  "Mud Brick": "tconstruct:materials:1",
  "Petty Tartaric Gem": "bloodmagic:ItemSoulGem:0:f62",
  "Pig Iron Hand Guard": "tconstruct:hand_guard:0:1d383047",
  "Machine Infuser": "rftools:machine_infuser:0",
  "Slime Binding": "tconstruct:binding:0:1424241f",
  "Minecart": "minecraft:minecart:0",
  "Black Stained Clay": "minecraft:stained_hardened_clay:15",
  "Redstone Ore": "minecraft:redstone_ore:0",
  "Elemental Inscription Tool: Water": "bloodmagic:ItemInscriptionTool:1",
  "Slime Sign Plate": "tconstruct:sign_head:0:1424241f",
  "Sigil of Compression": "bloodmagic:ItemSigilCompression:0",
  "Prismarine Tool Rod": "tconstruct:tool_rod:0:5bbd0ef3",
  "Counter Plus Module": "rftools:counterplus_module:0",
  "Seared Creeperface": "tconstruct:seared:8",
  "Reinforcement": "tconstruct:materials:14",
  "Light Gray Stained Glass": "minecraft:stained_glass:8",
  "Wooden Hoe": "minecraft:wooden_hoe:0",
  "Red Wool": "minecraft:wool:14",
  "Stone Hoe": "minecraft:stone_hoe:0",
  "Flint Excavator Head": "tconstruct:excavator_head:0:ea5d31a",
  "Block of Gold": "minecraft:gold_block:0",
  "Paper Axe Head": "tconstruct:axe_head:0:d3d5a7d",
  "Netherrack Pan": "tconstruct:pan_head:0:20beaa74",
  "Steadfast Will Crystal": "bloodmagic:ItemDemonCrystal:4",
  "Cactus Shovel Head": "tconstruct:shovel_head:0:3ea590f2",
  "Wooden Tough Binding": "tconstruct:tough_binding:0:156619f2",
  "Manyullyn Sign Plate": "tconstruct:sign_head:0:7484c1bc",
  "Obsidian Brick Path": "bloodmagic:BlockPath:6",
  "Redstone": "minecraft:redstone:0",
  "Stone Wide Guard": "tconstruct:wide_guard:0:cc51ef16",
  "Iron Trapdoor": "minecraft:iron_trapdoor:0",
  "Flint Shovel Head": "tconstruct:shovel_head:0:ea5d31a",
  "Knightslime Ingot": "tconstruct:ingots:3",
  "Orange Dye": "minecraft:dye:14",
  "Jack o\u0027Lantern": "minecraft:lit_pumpkin:0",
  "Master Ritual Stone": "bloodmagic:BlockRitualController:0",
  "Purpur Block": "minecraft:purpur_block:0",
  "Orphaning Card": "rftools:orphaning_card:0",
  "Purpur Slab": "minecraft:purpur_slab:0",
  "Obsidian Pickaxe Head": "tconstruct:pick_head:0:4df63d20",
  "Iron Excavator Head": "tconstruct:excavator_head:0:fdacad4d",
  "No Teleport Module": "rftools:noteleport_module:0",
  "Diamond Boots": "minecraft:diamond_boots:0",
  "Flint Axe Head": "tconstruct:axe_head:0:ea5d31a",
  "Oak Wood Stairs": "minecraft:oak_stairs:0",
  "Orange Stained Glass Pane": "minecraft:stained_glass_pane:1",
  "Sandstone Slab": "minecraft:stone_slab:1",
  "Pigiron Nugget": "tconstruct:nuggets:4",
  "Logic Gate": "rftools:logic_block:0",
  "Tiled Worn Stone Path": "bloodmagic:BlockPath:5",
  "Charging Rune": "bloodmagic:BlockBloodRune:10",
  "Prismarine Pickaxe Head": "tconstruct:pick_head:0:5bbd0ef3",
  "Sigil of Ender Severance": "bloodmagic:ItemSigilEnderSeverance:0",
  "Sandstone": "minecraft:sandstone:0",
  "Lingering Potion of Healing": "minecraft:lingering_potion:0:b4050032",
  "Prismarine Sign Plate": "tconstruct:sign_head:0:5bbd0ef3",
  "Pattern Chest": "tconstruct:tooltables:4",
  "End Sharpening Kit": "tconstruct:sharpening_kit:0:ccc1936f",
  "Shield Projector Tier 1": "rftools:shield_block1:0",
  "Shield Projector Tier 2": "rftools:shield_block2:0",
  "Seared Stone": "fluid:stone",
  "Silky Cloth": "tconstruct:materials:15",
  "Apple": "minecraft:apple:0",
  "Spruce Fence Gate": "minecraft:spruce_fence_gate:0",
  "Shield Projector Tier 3": "rftools:shield_block3:0",
  "Shield Projector Tier 4": "rftools:shield_block4:0",
  "Potion of Fire Resistance": "minecraft:potion:0:318abcfd",
  "Lingering Potion of Strength": "minecraft:lingering_potion:0:779a3b1f",
  "Tiled Stone Path": "bloodmagic:BlockPath:3",
  "Wooden Broad Axe Head": "tconstruct:broad_axe_head:0:156619f2",
  "RFTools Manual": "rftools:rftools_manual:0",
  "Reinforced Slate": "bloodmagic:ItemSlate:1",
  "Cyan Banner": "minecraft:banner:6",
  "Lingering Uncraftable Potion": "minecraft:lingering_potion:0:4b383f05",
  "Light Blue Wool": "minecraft:wool:3",
  "Bone Sign Plate": "tconstruct:sign_head:0:f18fe449",
  "Security Manager": "rftools:security_manager:0",
  "Manyullyn Shovel Head": "tconstruct:shovel_head:0:7484c1bc",
  "Generic Storage Module": "rftools:generic_module:0",
  "Armor Stand": "minecraft:armor_stand:0",
  "Firewood Broad Axe Head": "tconstruct:broad_axe_head:0:aa8d0aa8",
  "Energy Module": "rftools:energy_module:0",
  "Inventory Module": "rftools:inventory_module:0",
  "Living Leggings": "bloodmagic:ItemLivingArmourLegs:0",
  "End Axe Head": "tconstruct:axe_head:0:ccc1936f",
  "Acacia Fence Gate": "minecraft:acacia_fence_gate:0",
  "Firewood Sharpening Kit": "tconstruct:sharpening_kit:0:aa8d0aa8",
  "Sponge Excavator Head": "tconstruct:excavator_head:0:ea54e05f",
  "Potion of Poison": "minecraft:potion:0:228722a3",
  "Firewood Tough Binding": "tconstruct:tough_binding:0:aa8d0aa8",
  "Diamond Ore": "minecraft:diamond_ore:0",
  "Slime Sharpening Kit": "tconstruct:sharpening_kit:0:1424241f",
  "Ritual Stone of Air": "bloodmagic:BlockRitualStone:4",
  "Magma Slime Block": "tconstruct:slime:4",
  "Dagger of Sacrifice": "bloodmagic:ItemDaggerOfSacrifice:0",
  "Chiseled Quartz Block": "minecraft:quartz_block:1",
  "Clock Module": "rftools:clock_module:0",
  "Slime Axe Head": "tconstruct:axe_head:0:1424241f",
  "Hardened Clay": "minecraft:hardened_clay:0",
  "Tome of Peritia": "bloodmagic:ItemExperienceBook:0",
  "Ardite Hand Guard": "tconstruct:hand_guard:0:f34653ac",
  "Weak Activation Crystal": "bloodmagic:ItemActivationCrystal:0",
  "Haste Plus Module": "rftools:hasteplus_module:0",
  "Slime Broad Axe Head": "tconstruct:broad_axe_head:0:1424241f",
  "Spruce Boat": "minecraft:spruce_boat:0",
  "Thick Potion": "minecraft:potion:0:5bc2e955",
  "Bucket": "minecraft:bucket:0",
  "Manyullyn Excavator Head": "tconstruct:excavator_head:0:7484c1bc",
  "Prismarine Crystals": "minecraft:prismarine_crystals:0",
  "End Hand Guard": "tconstruct:hand_guard:0:ccc1936f",
  "Aluminum Brass Ingot": "tconstruct:ingots:5",
  "Ritual Diviner [Dusk]": "bloodmagic:ItemRitualDiviner:1",
  "Birch Wood Stairs": "minecraft:birch_stairs:0",
  "End Stone Bricks": "minecraft:end_bricks:0",
  "Nether Wart": "minecraft:nether_wart:0",
  "Prismarine Shovel Head": "tconstruct:shovel_head:0:5bbd0ef3",
  "Magma Slime Large Sword Blade": "tconstruct:large_sword_blade:0:ceaf4bc6",
  "Shape Card (Silk Quarry)": "rftools:shape_card:3",
  "Flint": "minecraft:flint:0",
  "Knightslime Nugget": "tconstruct:nuggets:3",
  "Firewood Tool Rod": "tconstruct:tool_rod:0:aa8d0aa8",
  "Teleposition Focus": "bloodmagic:ItemTelepositionFocus:0",
  "Blank Cast": "tconstruct:cast:0",
  "Congealed Blue Slime Block": "tconstruct:slime_congealed:1",
  "Block of Aluminum Brass": "tconstruct:metal:5",
  "Acacia Boat": "minecraft:acacia_boat:0",
  "End Hammer Head": "tconstruct:hammer_head:0:ccc1936f",
  "Red Sandstone Stairs": "minecraft:red_sandstone_stairs:0",
  "Stone Bricks Slab": "minecraft:stone_slab:5",
  "Birch Boat": "minecraft:birch_boat:0",
  "Knightslime Broad Axe Head": "tconstruct:broad_axe_head:0:eb40d90c",
  "Cobblestone": "minecraft:cobblestone:0",
  "Podzol": "minecraft:dirt:2",
  "Block of Quartz": "minecraft:quartz_block:0",
  "Spruce Wood Slab": "minecraft:wooden_slab:1",
  "Dark Oak Fence": "minecraft:dark_oak_fence:0",
  "Manyullyn Binding": "tconstruct:binding:0:7484c1bc",
  "Corrosive Will Crystal": "bloodmagic:ItemDemonCrystal:1",
  "Part Chest": "tconstruct:tooltables:5",
  "Red Sandstone": "minecraft:red_sandstone:0",
  "Firewood Large Plate": "tconstruct:large_plate:0:aa8d0aa8",
  "Minecart with Hopper": "minecraft:hopper_minecart:0",
  "Divination Sigil": "bloodmagic:ItemSigilDivination:0",
  "Oak Fence Gate": "minecraft:fence_gate:0",
  "Sponge Large Sword Blade": "tconstruct:large_sword_blade:0:ea54e05f",
  "Wooden Shovel": "minecraft:wooden_shovel:0",
  "Black Stained Glass": "minecraft:stained_glass:15",
  "Cactus Axe Head": "tconstruct:axe_head:0:3ea590f2",
  "Ardite Pan": "tconstruct:pan_head:0:f34653ac",
  "Slime Boots": "tconstruct:slime_boots:0",
  "Saturation Plus Module": "rftools:saturationplus_module:0",
  "White Banner": "minecraft:banner:15",
  "Purple Stained Clay": "minecraft:stained_hardened_clay:10",
  "Sharpening Kit Clay Cast": "tconstruct:clay_cast:0:e2749cc8",
  "Energy Plus Module": "rftools:energyplus_module:0",
  "Jungle Sapling": "minecraft:sapling:3",
  "Stone Large Sword Blade": "tconstruct:large_sword_blade:0:cc51ef16",
  "Leather Tunic": "minecraft:leather_chestplate:0",
  "Inventory Plus Module": "rftools:inventoryplus_module:0",
  "Hopper": "minecraft:hopper:0",
  "Pearl Injector": "rftools:pearl_injector:0",
  "Yellow Stained Clay": "minecraft:stained_hardened_clay:4",
  "Cooked Chicken": "minecraft:cooked_chicken:0",
  "Stone Sword Blade": "tconstruct:sword_blade:0:cc51ef16",
  "Redstone Torch": "minecraft:redstone_torch:0",
  "Magma Slime Hand Guard": "tconstruct:hand_guard:0:ceaf4bc6",
  "Pig Iron Excavator Head": "tconstruct:excavator_head:0:1d383047",
  "Dirt": "minecraft:dirt:0",
  "Block of Diamond": "minecraft:diamond_block:0",
  "Purpur Pillar": "minecraft:purpur_pillar:0",
  "Blue Slime Block": "tconstruct:slime:1",
  "Manyullyn Wide Guard": "tconstruct:wide_guard:0:7484c1bc",
  "Wide Guard Clay Cast": "tconstruct:clay_cast:0:f4bbbe3b",
  "Paper Large Sword Blade": "tconstruct:large_sword_blade:0:d3d5a7d",
  "Feather Falling Plus Module": "rftools:featherfallingplus_module:0",
  "Counter": "rftools:counter_block:0",
  "Chiseled Red Sandstone": "minecraft:red_sandstone:1",
  "Coal": "minecraft:coal:0",
  "Sponge Large Plate": "tconstruct:large_plate:0:ea54e05f",
  "Coat of Arms": "bloodmagic:ItemPackSacrifice:0",
  "Sponge Tough Tool Rod": "tconstruct:tough_tool_rod:0:ea54e05f",
  "Magma Slime Shard": "tconstruct:shard:0:ceaf4bc6",
  "Congealed Purple Slime Block": "tconstruct:slime_congealed:2",
  "Casting Basin": "tconstruct:casting:1",
  "Pig Iron Shovel Head": "tconstruct:shovel_head:0:1d383047",
  "Corrosive Will Crystal Cluster": "bloodmagic:BlockDemonCrystal:1",
  "Splash Potion of Fire Resistance": "minecraft:splash_potion:0:318abcfd",
  "Ritual Stone of Fire": "bloodmagic:BlockRitualStone:2",
  "Diamond Sword": "minecraft:diamond_sword:0",
  "Slime Block": "minecraft:slime:0",
  "Wooden Axe": "minecraft:wooden_axe:0",
  "Dropper": "minecraft:dropper:0",
  "Golden Boots": "minecraft:golden_boots:0",
  "Glowstone": "minecraft:glowstone:0",
  "Raw Porkchop": "minecraft:porkchop:0",
  "Gray Stained Clay": "minecraft:stained_hardened_clay:7",
  "Knightslime Sharpening Kit": "tconstruct:sharpening_kit:0:eb40d90c",
  "Living Boots": "bloodmagic:ItemLivingArmourBoots:0",
  "Raw Fish": "minecraft:fish:0",
  "Splash Potion of Weakness": "minecraft:splash_potion:0:98548baa",
  "Enchanted Book": "minecraft:enchanted_book:0",
  "Raw Chicken": "minecraft:chicken:0",
  "Wooden Sword Blade": "tconstruct:sword_blade:0:156619f2",
  "Feather Falling Module": "rftools:featherfalling_module:0",
  "Yellow Stained Glass Pane": "minecraft:stained_glass_pane:4",
  "Pumpkin Seeds": "minecraft:pumpkin_seeds:0",
  "Storage Control Module": "rftools:storage_control_module:0",
  "Stone Axe": "minecraft:stone_axe:0",
  "Prismarine Tough Binding": "tconstruct:tough_binding:0:5bbd0ef3",
  "Knightslime Tool Rod": "tconstruct:tool_rod:0:eb40d90c",
  "Stone Pickaxe": "minecraft:stone_pickaxe:0",
  "Golden Apple": "minecraft:golden_apple:0",
  "Cooked Salmon": "minecraft:cooked_fish:1",
  "Imperfect Ritual Stone": "bloodmagic:BlockRitualController:1",
  "Magma Slime Binding": "tconstruct:binding:0:ceaf4bc6",
  "Firewood Tough Tool Rod": "tconstruct:tough_tool_rod:0:aa8d0aa8",
  "Dark Oak Boat": "minecraft:dark_oak_boat:0",
  "Purple Carpet": "minecraft:carpet:10",
  "Splash Potion of Regeneration": "minecraft:splash_potion:0:b662a5ab",
  "Water Reagent": "bloodmagic:ItemComponent:0",
  "Stone Sign Plate": "tconstruct:sign_head:0:cc51ef16",
  "Orange Stained Glass": "minecraft:stained_glass:1",
  "Knightslime Shard": "tconstruct:shard:0:eb40d90c",
  "Sugar": "minecraft:sugar:0",
  "Block of Redstone": "minecraft:redstone_block:0",
  "Beetroot": "minecraft:beetroot:0",
  "Emerald Ore": "minecraft:emerald_ore:0",
  "Teleposition Reagent": "bloodmagic:ItemComponent:17",
  "Acacia Sapling": "minecraft:sapling:4",
  "Shape Card (Void)": "rftools:shape_card:1",
  "Jungle Fence Gate": "minecraft:jungle_fence_gate:0",
  "Ore Dictionary Storage Module": "rftools:oredict_module:0",
  "Paper Sign Plate": "tconstruct:sign_head:0:d3d5a7d",
  "Yellow Carpet": "minecraft:carpet:4",
  "Potion of Regeneration": "minecraft:potion:0:b0e1b266",
  "Blue Slime Crystal": "tconstruct:materials:10",
  "Stone Slab": "minecraft:stone_slab:0",
  "Air Reagent": "bloodmagic:ItemComponent:2",
  "Manyullyn Pickaxe Head": "tconstruct:pick_head:0:7484c1bc",
  "Packed Ice": "minecraft:packed_ice:0",
  "Prismarine Wide Guard": "tconstruct:wide_guard:0:5bbd0ef3",
  "Sign": "minecraft:sign:0",
  "Iron Hand Guard": "tconstruct:hand_guard:0:fdacad4d",
  "Advanced Charged Porter": "rftools:advanced_charged_porter:0",
  "Gold Ore": "minecraft:gold_ore:0",
  "Axe Head Cast": "tconstruct:cast:0:d1028c33",
  "Netherrack Hand Guard": "tconstruct:hand_guard:0:20beaa74",
  "Counter Module": "rftools:counter_module:0",
  "End Wide Guard": "tconstruct:wide_guard:0:ccc1936f",
  "Pig Iron Axe Head": "tconstruct:axe_head:0:1d383047",
  "Splash Potion of Harming": "minecraft:splash_potion:0:a53c0824",
  "Sigil of the Blood Lamp": "bloodmagic:ItemSigilBloodLight:0",
  "Pig Iron Shard": "tconstruct:shard:0:1d383047",
  "Black Banner": "minecraft:banner:0",
  "Wide Guard Cast": "tconstruct:cast:0:f4bbbe3b",
  "Pan Cast": "tconstruct:cast:0:7614c7c4",
  "Flint Tough Tool Rod": "tconstruct:tough_tool_rod:0:ea5d31a",
  "Quartz Slab": "minecraft:stone_slab:7",
  "Stone Binding": "tconstruct:binding:0:cc51ef16",
  "Firewood Shard": "tconstruct:shard:0:aa8d0aa8",
  "Pufferfish": "minecraft:fish:3",
  "Golden Axe": "minecraft:golden_axe:0",
  "Transcendent Blood Orb": "bloodmagic:ItemBloodOrb:5",
  "Lingering Potion of Regeneration": "minecraft:lingering_potion:0:4bfd1a69",
  "Elevator Button Module": "rftools:elevator_button_module:0",
  "Flint Shard": "tconstruct:shard:0:ea5d31a",
  "Lime Stained Clay": "minecraft:stained_hardened_clay:5",
  "End Stone": "minecraft:end_stone:0",
  "Prismarine Excavator Head": "tconstruct:excavator_head:0:5bbd0ef3",
  "Cobblestone Stairs": "minecraft:stone_stairs:0",
  "Acacia Wood": "minecraft:log2:0",
  "Large Sword Blade Cast": "tconstruct:cast:0:15a430e6",
  "Poison Module": "rftools:poison_module:0",
  "Splash Potion of Swiftness": "minecraft:splash_potion:0:e2dae2e0",
  "Stone Shard": "tconstruct:shard:0:cc51ef16",
  "Smeltery Controller": "tconstruct:smeltery_controller:0",
  "Hammer Head Clay Cast": "tconstruct:clay_cast:0:b990094d",
  "Matter Transmitter": "rftools:matter_transmitter:0",
  "Iron Axe Head": "tconstruct:axe_head:0:fdacad4d",
  "Brown Stained Glass Pane": "minecraft:stained_glass_pane:12",
  "Carrot": "minecraft:carrot:0",
  "Stone Pressure Plate": "minecraft:stone_pressure_plate:0",
  "Silky Block of Jewel": "tconstruct:metal:6",
  "Blue Stained Glass": "minecraft:stained_glass:11",
  "Potion of Healing": "minecraft:potion:0:bfc1f3b0",
  "Leather": "minecraft:leather:0",
  "Lapis Lazuli Ore": "minecraft:lapis_ore:0",
  "Weighted Pressure Plate (Heavy)": "minecraft:heavy_weighted_pressure_plate:0",
  "Tough Tool Rod Cast": "tconstruct:cast:0:87e83866",
  "Rune of Self Sacrifice": "bloodmagic:BlockBloodRune:4",
  "Flower Pot": "minecraft:flower_pot:0",
  "Cobalt Shovel Head": "tconstruct:shovel_head:0:207823b8",
  "Iron Pickaxe": "minecraft:iron_pickaxe:0",
  "Mundane Lingering Potion": "minecraft:lingering_potion:0:b90772f2",
  "Sword Blade Clay Cast": "tconstruct:clay_cast:0:ed0275aa",
  "Slime Excavator Head": "tconstruct:excavator_head:0:1424241f",
  "End Shard": "tconstruct:shard:0:ccc1936f",
  "Cactus Tough Tool Rod": "tconstruct:tough_tool_rod:0:3ea590f2",
  "Wooden Pickaxe Head": "tconstruct:pick_head:0:156619f2",
  "Sponge Axe Head": "tconstruct:axe_head:0:ea54e05f",
  "Redstone Module": "rftools:redstone_module:0",
  "Arrow of Regeneration": "minecraft:tipped_arrow:0:4bfd1a69",
  "Slime Pickaxe Head": "tconstruct:pick_head:0:1424241f",
  "Ardite Axe Head": "tconstruct:axe_head:0:f34653ac",
  "Reinforced Teleposition Focus": "bloodmagic:ItemTelepositionFocus:2",
  "Blue Slimy Mud": "tconstruct:soil:2",
  "Molten Clay": "fluid:clay",
  "Sigil of Haste": "bloodmagic:ItemSigilHaste:0",
  "Awkward Lingering Potion": "minecraft:lingering_potion:0:174fc869",
  "Grout": "tconstruct:soil:0",
  "Blue Slime Sapling": "tconstruct:slime_sapling:0",
  "Glistering Melon": "minecraft:speckled_melon:0",
  "End Tool Rod": "tconstruct:tool_rod:0:ccc1936f",
  "Obsidian Wide Guard": "tconstruct:wide_guard:0:4df63d20",
  "Light Gray Stained Clay": "minecraft:stained_hardened_clay:8",
  "Iron Sign Plate": "tconstruct:sign_head:0:fdacad4d",
  "Pumpkin": "minecraft:pumpkin:0",
  "Blaze Rod": "minecraft:blaze_rod:0",
  "Iron Binding": "tconstruct:binding:0:fdacad4d",
  "Rune of the Orb": "bloodmagic:BlockBloodRune:8",
  "Arrow of Luck": "minecraft:tipped_arrow:0:615e640f",
  "Water Breathing Module": "rftools:waterbreathing_module:0",
  "Tiled Wooden Path": "bloodmagic:BlockPath:1",
  "Cobalt Shard": "tconstruct:shard:0:207823b8",
  "Rune of Sacrifice": "bloodmagic:BlockBloodRune:3",
  "Wooden Pressure Plate": "minecraft:wooden_pressure_plate:0",
  "Magma Slime Hammer Head": "tconstruct:hammer_head:0:ceaf4bc6",
  "Blue Wool": "minecraft:wool:11",
  "Gunpowder": "minecraft:gunpowder:0",
  "Mushroom Stew": "minecraft:mushroom_stew:0",
  "Manyullyn Sharpening Kit": "tconstruct:sharpening_kit:0:7484c1bc",
  "Block of Emerald": "minecraft:emerald_block:0",
  "Molten Emerald": "fluid:emerald",
  "Diamond Pickaxe": "minecraft:diamond_pickaxe:0",
  "Minecart with Furnace": "minecraft:furnace_minecart:0",
  "Prismarine Sharpening Kit": "tconstruct:sharpening_kit:0:5bbd0ef3",
  "Wooden Trapdoor": "minecraft:trapdoor:0",
  "Wooden Wide Guard": "tconstruct:wide_guard:0:156619f2",
  "Sponge Shard": "tconstruct:shard:0:ea54e05f",
  "Obsidian Tough Tool Rod": "tconstruct:tough_tool_rod:0:4df63d20",
  "Slime Shovel Head": "tconstruct:shovel_head:0:1424241f",
  "Gray Wool": "minecraft:wool:7",
  "Lilac": "minecraft:double_plant:1",
  "Prismarine Hammer Head": "tconstruct:hammer_head:0:5bbd0ef3",
  "Stone Brick Path": "bloodmagic:BlockPath:2",
  "Spruce Door": "minecraft:spruce_door:0",
  "Ender Monitor": "rftools:ender_monitor:0",
  "Wooden Large Plate": "tconstruct:large_plate:0:156619f2",
  "Cyan Stained Glass": "minecraft:stained_glass:9",
  "Paper Large Plate": "tconstruct:large_plate:0:d3d5a7d",
  "Weak Blood Shard": "bloodmagic:ItemBloodShard:0",
  "Efficiency Rune": "bloodmagic:BlockBloodRune:2",
  "Stone Excavator Head": "tconstruct:excavator_head:0:cc51ef16",
  "Fluid Plus Module": "rftools:fluidplus_module:0",
  "Green Slime Block": "tconstruct:slime:0",
  "Awakened Activation Crystal": "bloodmagic:ItemActivationCrystal:1",
  "Prismarine Binding": "tconstruct:binding:0:5bbd0ef3",
  "Large Sword Blade Clay Cast": "tconstruct:clay_cast:0:15a430e6",
  "Jungle Boat": "minecraft:jungle_boat:0",
  "Paper Hand Guard": "tconstruct:hand_guard:0:d3d5a7d",
  "Splash Potion of Invisibility": "minecraft:splash_potion:0:1ba7f9d2",
  "Bone Pickaxe Head": "tconstruct:pick_head:0:f18fe449",
  "Graveyard Soil": "tconstruct:soil:3",
  "Birch Wood Slab": "minecraft:wooden_slab:2",
  "Seared Tank": "tconstruct:seared_tank:0",
  "Soul Sand": "minecraft:soul_sand:0",
  "Manyullyn Broad Axe Head": "tconstruct:broad_axe_head:0:7484c1bc",
  "Pig Iron Wide Guard": "tconstruct:wide_guard:0:1d383047",
  "Rabbit Stew": "minecraft:rabbit_stew:0",
  "Button Module": "rftools:button_module:0",
  "Prismarine Broad Axe Head": "tconstruct:broad_axe_head:0:5bbd0ef3",
  "Green Banner": "minecraft:banner:2",
  "Potion of Water Breathing": "minecraft:potion:0:f56a775",
  "Pickaxe Head Cast": "tconstruct:cast:0:97ab71d2",
  "Potion of Night Vision": "minecraft:potion:0:27447fca",
  "Bone Meal": "minecraft:dye:15",
  "Tool Forge": "tconstruct:toolforge:0:d67f5fd4",
  "Glass Pane": "minecraft:glass_pane:0",
  "Detector Rail": "minecraft:detector_rail:0",
  "Oxeye Daisy": "minecraft:red_flower:8",
  "Shovel Head Cast": "tconstruct:cast:0:802428d0",
  "Birch Door": "minecraft:birch_door:0",
  "Iron Axe": "minecraft:iron_axe:0",
  "Trapped Chest": "minecraft:trapped_chest:0",
  "Mod Item Filter": "bloodmagic:ItemRouterFilter:2",
  "End Large Sword Blade": "tconstruct:large_sword_blade:0:ccc1936f",
  "Ritual Stone of Water": "bloodmagic:BlockRitualStone:1",
  "Magma Slime Tool Rod": "tconstruct:tool_rod:0:ceaf4bc6",
  "Manyullyn Pan": "tconstruct:pan_head:0:7484c1bc",
  "Cobalt Tough Binding": "tconstruct:tough_binding:0:207823b8",
  "Rotten Flesh": "minecraft:rotten_flesh:0",
  "Wool": "minecraft:wool:0",
  "Melon": "minecraft:melon:0",
  "Master Routing Node": "bloodmagic:BlockMasterRoutingNode:0",
  "Greater Tartaric Gem": "bloodmagic:ItemSoulGem:3:f62",
  "Minecart with Chest": "minecraft:chest_minecart:0",
  "Crafting Table": "minecraft:crafting_table:0",
  "Slowness Module": "rftools:slowness_module:0",
  "Gold Nugget": "minecraft:gold_nugget:0",
  "Carpet": "minecraft:carpet:0",
  "Thick Lingering Potion": "minecraft:lingering_potion:0:5bc2e955",
  "Haste Module": "rftools:haste_module:0",
  "Netherrack Tough Tool Rod": "tconstruct:tough_tool_rod:0:20beaa74",
  "Ritual Diviner": "bloodmagic:ItemRitualDiviner:0",
  "Bread": "minecraft:bread:0",
  "Crafter Tier 1": "rftools:crafter1:0",
  "Crafter Tier 2": "rftools:crafter2:0",
  "Ardite Item Frame": "tconstruct:fancy_frame:3",
  "Raw Beef": "minecraft:beef:0",
  "Ink Sac": "minecraft:dye:0",
  "Stone Shovel Head": "tconstruct:shovel_head:0:cc51ef16",
  "Liquid Monitor": "rftools:liquid_monitor:0",
  "Piston": "minecraft:piston:0",
  "Netherrack Axe Head": "tconstruct:axe_head:0:20beaa74",
  "Stone Axe Head": "tconstruct:axe_head:0:cc51ef16",
  "Simple Dialer": "rftools:simple_dialer:0",
  "Crafter Tier 3": "rftools:crafter3:0",
  "Lingering Potion of Slowness": "minecraft:lingering_potion:0:fe290b73",
  "Sea Lantern": "minecraft:sea_lantern:0",
  "Ingot Cast": "tconstruct:cast_custom:0",
  "Flint Hand Guard": "tconstruct:hand_guard:0:ea5d31a",
  "Cooked Fish": "minecraft:cooked_fish:0",
  "Obsidian Pan": "tconstruct:pan_head:0:4df63d20",
  "Dialing Device": "rftools:dialing_device:0",
  "Sponge Sword Blade": "tconstruct:sword_blade:0:ea54e05f",
  "Lingering Water Bottle": "minecraft:lingering_potion:0:ef1fb44f",
  "Flint Tool Rod": "tconstruct:tool_rod:0:ea5d31a",
  "Bone Sword Blade": "tconstruct:sword_blade:0:f18fe449",
  "Obsidian Large Plate": "tconstruct:large_plate:0:4df63d20",
  "Magenta Stained Glass Pane": "minecraft:stained_glass_pane:2",
  "Knightslime Wide Guard": "tconstruct:wide_guard:0:eb40d90c",
  "Cactus Hand Guard": "tconstruct:hand_guard:0:3ea590f2",
  "Lime Dye": "minecraft:dye:10",
  "Arrow of Fire Resistance": "minecraft:tipped_arrow:0:2bd7b21a",
  "Blank Pattern": "tconstruct:pattern:0",
  "Glass": "minecraft:glass:0",
  "Crystal Cluster": "bloodmagic:BlockCrystal:0",
  "Firewood Wide Guard": "tconstruct:wide_guard:0:aa8d0aa8",
  "Speed Rune": "bloodmagic:BlockBloodRune:1",
  "Arrow of Healing": "minecraft:tipped_arrow:0:b4050032",
  "Iron Pickaxe Head": "tconstruct:pick_head:0:fdacad4d",
  "Transposition Reagent": "bloodmagic:ItemComponent:18",
  "Void Reagent": "bloodmagic:ItemComponent:4",
  "Growth Reagent": "bloodmagic:ItemComponent:5",
  "Popped Chorus Fruit": "minecraft:chorus_fruit_popped:0",
  "Netherrack Shard": "tconstruct:shard:0:20beaa74",
  "Tough Binding Clay Cast": "tconstruct:clay_cast:0:f93bf55",
  "Red Stained Glass": "minecraft:stained_glass:14",
  "Lead": "minecraft:lead:0",
  "Cocoa Beans": "minecraft:dye:3",
  "Congealed Green Slime Block": "tconstruct:slime_congealed:0",
  "Sponge Tool Rod": "tconstruct:tool_rod:0:ea54e05f",
  "Night Vision Module": "rftools:nightvision_module:0",
  "Storage Module Tablet": "rftools:storage_module_tablet:1",
  "Seer\u0027s Sigil": "bloodmagic:ItemSigilSeer:0",
  "Lingering Potion of Poison": "minecraft:lingering_potion:0:228722a3",
  "Poppy": "minecraft:red_flower:0",
  "Wooden Sharpening Kit": "tconstruct:sharpening_kit:0:156619f2",
  "Water Sigil": "bloodmagic:ItemSigilWater:0",
  "Water Bottle": "minecraft:potion:0:ef1fb44f",
  "Cobalt Tough Tool Rod": "tconstruct:tough_tool_rod:0:207823b8",
  "Bricks": "minecraft:brick_block:0",
  "End Large Plate": "tconstruct:large_plate:0:ccc1936f",
  "Magician Blood Orb": "bloodmagic:ItemBloodOrb:2",
  "Arrow of Weakness": "minecraft:tipped_arrow:0:f0126d2d",
  "Brown Banner": "minecraft:banner:3",
  "Oak Wood Planks": "minecraft:planks:0",
  "Fancy Seared Bricks": "tconstruct:seared:5",
  "Anvil": "minecraft:anvil:0",
  "Potion of Leaping": "minecraft:potion:0:21dbbc95",
  "Grass Block": "minecraft:grass:0",
  "Shape Card (Quarry)": "rftools:shape_card:2",
  "Demon Blood Shard": "bloodmagic:ItemBloodShard:1",
  "Powered Rail": "minecraft:golden_rail:0",
  "End Broad Axe Head": "tconstruct:broad_axe_head:0:ccc1936f",
  "Dragon\u0027s Breath": "minecraft:dragon_breath:0",
  "Stone Pickaxe Head": "tconstruct:pick_head:0:cc51ef16",
  "Sentient Armour Gem": "bloodmagic:ItemSentientArmourGem:0",
  "Red Sand": "minecraft:sand:1",
  "Ardite Tool Rod": "tconstruct:tool_rod:0:f34653ac",
  "Potion of Slowness": "minecraft:potion:0:fe290b73",
  "Punji Sticks": "tconstruct:punji:0",
  "Charcoal": "minecraft:coal:1",
  "Remote Storage": "rftools:remote_storage:0",
  "Arrow of Strength": "minecraft:tipped_arrow:0:779a3b1f",
  "Stone Bricks": "minecraft:stonebrick:0",
  "Stone Broad Axe Head": "tconstruct:broad_axe_head:0:cc51ef16",
  "Polished Andesite": "minecraft:stone:6",
  "Golden Carrot": "minecraft:golden_carrot:0",
  "End Tough Binding": "tconstruct:tough_binding:0:ccc1936f",
  "Paper Tough Binding": "tconstruct:tough_binding:0:d3d5a7d",
  "Wooden Hammer Head": "tconstruct:hammer_head:0:156619f2",
  "Stone Sharpening Kit": "tconstruct:sharpening_kit:0:cc51ef16",
  "Seared Bricks": "tconstruct:seared:3",
  "Gray Stained Glass": "minecraft:stained_glass:7",
  "Coal Ore": "minecraft:coal_ore:0",
  "Bone Wide Guard": "tconstruct:wide_guard:0:f18fe449",
  "Paper Hammer Head": "tconstruct:hammer_head:0:d3d5a7d",
  "Cooked Mutton": "minecraft:cooked_mutton:0",
  "Block of Pigiron": "tconstruct:metal:4",
  "End Rod": "minecraft:end_rod:0",
  "Cactus": "minecraft:cactus:0",
  "Iron Tool Rod": "tconstruct:tool_rod:0:fdacad4d",
  "Cyan Dye": "minecraft:dye:6",
  "Storage Module Tier 3": "rftools:storage_module:2",
  "Prismarine Bricks": "minecraft:prismarine:1",
  "Steadfast Will Crystal Cluster": "bloodmagic:BlockDemonCrystal:4",
  "Storage Module Tier 1": "rftools:storage_module:0",
  "Storage Module Tier 2": "rftools:storage_module:1",
  "Smeltery Drain": "tconstruct:smeltery_io:0",
  "Ardite Shovel Head": "tconstruct:shovel_head:0:f34653ac",
  "Chorus Fruit": "minecraft:chorus_fruit:0",
  "Large Bloodstone Brick": "bloodmagic:BlockBloodStoneBrick:0",
  "Cobalt Tool Rod": "tconstruct:tool_rod:0:207823b8",
  "Pink Stained Glass": "minecraft:stained_glass:6",
  "Firewood Shovel Head": "tconstruct:shovel_head:0:aa8d0aa8",
  "Netherrack Tough Binding": "tconstruct:tough_binding:0:20beaa74",
  "Jungle Wood Planks": "minecraft:planks:3",
  "Item Filter": "rftools:item_filter:0",
  "Orange Wool": "minecraft:wool:1",
  "Power Relay": "rftools:relay:0",
  "Ardite Ore": "tconstruct:ore:1",
  "Regeneration Module": "rftools:regeneration_module:0",
  "Iron Tough Tool Rod": "tconstruct:tough_tool_rod:0:fdacad4d",
  "Cactus Pickaxe Head": "tconstruct:pick_head:0:3ea590f2",
  "Coarse Dirt": "minecraft:dirt:1",
  "Water Bucket": "minecraft:water_bucket:0",
  "Manyullyn Nugget": "tconstruct:nuggets:2",
  "Cactus Sword Blade": "tconstruct:sword_blade:0:3ea590f2",
  "Routing Node": "bloodmagic:BlockItemRoutingNode:0",
  "Iron Leggings": "minecraft:iron_leggings:0",
  "Wet Sponge": "minecraft:sponge:1",
  "Obsidian Sign Plate": "tconstruct:sign_head:0:4df63d20",
  "End Sign Plate": "tconstruct:sign_head:0:ccc1936f",
  "Powercell Card": "rftools:powercell_card:0",
  "Pig Iron Large Plate": "tconstruct:large_plate:0:1d383047",
  "Lime Wool": "minecraft:wool:5",
  "Imbued Slate": "bloodmagic:ItemSlate:2",
  "Jukebox": "minecraft:jukebox:0",
  "Pig Iron Pickaxe Head": "tconstruct:pick_head:0:1d383047",
  "Cobalt Pickaxe Head": "tconstruct:pick_head:0:207823b8",
  "Wooden Sign Plate": "tconstruct:sign_head:0:156619f2",
  "Knightslime Large Sword Blade": "tconstruct:large_sword_blade:0:eb40d90c",
  "Knightslime Pickaxe Head": "tconstruct:pick_head:0:eb40d90c",
  "Oak Wood": "minecraft:log:0",
  "Bound Axe": "bloodmagic:ItemBoundAxe:0",
  "Coal Generator": "rftools:coalgenerator:0",
  "Wooden Excavator Head": "tconstruct:excavator_head:0:156619f2",
  "Sticky Piston": "minecraft:sticky_piston:0",
  "Sentient Sword": "bloodmagic:ItemSentientSword:0",
  "Paper Tough Tool Rod": "tconstruct:tough_tool_rod:0:d3d5a7d",
  "Timer": "rftools:timer_block:0",
  "Brick": "minecraft:brick:0",
  "Light Gray Banner": "minecraft:banner:7",
  "Blood Lamp Reagent": "bloodmagic:ItemComponent:11",
  "Magma Slime Large Plate": "tconstruct:large_plate:0:ceaf4bc6",
  "Elemental Inscription Tool: Dusk": "bloodmagic:ItemInscriptionTool:5",
  "Oak Sapling": "minecraft:sapling:0",
  "Iron Sharpening Kit": "tconstruct:sharpening_kit:0:fdacad4d",
  "RF Monitor": "rftools:rf_monitor:0",
  "Grand Tartaric Gem": "bloodmagic:ItemSoulGem:4:f62",
  "Ardite Wide Guard": "tconstruct:wide_guard:0:f34653ac",
  "Dark Oak Wood Stairs": "minecraft:dark_oak_stairs:0",
  "Redstone Comparator": "minecraft:comparator:0",
  "Block of Iron": "minecraft:iron_block:0",
  "Lingering Potion of Invisibility": "minecraft:lingering_potion:0:1ba7f9d2",
  "Gray Stained Glass Pane": "minecraft:stained_glass_pane:7",
  "End Shovel Head": "tconstruct:shovel_head:0:ccc1936f",
  "Magma Slime Tough Tool Rod": "tconstruct:tough_tool_rod:0:ceaf4bc6",
  "Button": "minecraft:wooden_button:0",
  "Pink Stained Glass Pane": "minecraft:stained_glass_pane:6",
  "Sight Reagent": "bloodmagic:ItemComponent:7",
  "Flint Wide Guard": "tconstruct:wide_guard:0:ea5d31a",
  "Polished Granite": "minecraft:stone:2",
  "Pink Banner": "minecraft:banner:9",
  "Light Gray Dye": "minecraft:dye:7",
  "Glass Bottle": "minecraft:glass_bottle:0",
  "Square Seared Bricks": "tconstruct:seared:6",
  "Iron Ingot": "minecraft:iron_ingot:0",
  "Sponge Hand Guard": "tconstruct:hand_guard:0:ea54e05f",
  "Lime Banner": "minecraft:banner:10",
  "Text Module": "rftools:text_module:0",
  "Purpur Stairs": "minecraft:purpur_stairs:0",
  "Iron Bars": "minecraft:iron_bars:0",
  "Green Stained Glass": "minecraft:stained_glass:13",
  "Iron Sword Blade": "tconstruct:sword_blade:0:fdacad4d",
  "Cyan Stained Clay": "minecraft:stained_hardened_clay:9",
  "Rose Bush": "minecraft:double_plant:4",
  "Iron Broad Axe Head": "tconstruct:broad_axe_head:0:fdacad4d",
  "Redstone Lamp": "minecraft:redstone_lamp:0",
  "Wooden Sword": "minecraft:wooden_sword:0",
  "Manyullyn Hammer Head": "tconstruct:hammer_head:0:7484c1bc",
  "Paper Tool Rod": "tconstruct:tool_rod:0:d3d5a7d",
  "Molten Cobalt": "fluid:cobalt",
  "Luck Module": "rftools:luck_module:0",
  "Wooden Pan": "tconstruct:pan_head:0:156619f2",
  "Glowing Module": "rftools:glowing_module:0",
  "Pig Iron Broad Axe Head": "tconstruct:broad_axe_head:0:1d383047",
  "Sandstone Stairs": "minecraft:sandstone_stairs:0",
  "Firewood Excavator Head": "tconstruct:excavator_head:0:aa8d0aa8",
  "Nugget Cast": "tconstruct:cast_custom:1",
  "Elemental Affinity Reagent": "bloodmagic:ItemComponent:6",
  "Slime Large Sword Blade": "tconstruct:large_sword_blade:0:1424241f",
  "Arrow of Poison": "minecraft:tipped_arrow:0:228722a3",
  "Excavator Head Clay Cast": "tconstruct:clay_cast:0:2c79a446",
  "Iron Shovel": "minecraft:iron_shovel:0",
  "Gold Ingot": "minecraft:gold_ingot:0",
  "Leather Boots": "minecraft:leather_boots:0",
  "Molten Ardite": "fluid:ardite",
  "Carrot on a Stick": "minecraft:carrot_on_a_stick:0",
  "Large Plate Clay Cast": "tconstruct:clay_cast:0:76924066",
  "Firewood": "tconstruct:firewood:1",
  "Arrow of Night Vision": "minecraft:tipped_arrow:0:c25fe7cd",
  "Transposition Sigil": "bloodmagic:ItemSigilTransposition:0",
  "Stone Sword": "minecraft:stone_sword:0",
  "Paper Shovel Head": "tconstruct:shovel_head:0:d3d5a7d",
  "Prismarine Large Plate": "tconstruct:large_plate:0:5bbd0ef3",
  "Magma Slime Pan": "tconstruct:pan_head:0:ceaf4bc6",
  "Obsidian Excavator Head": "tconstruct:excavator_head:0:4df63d20",
  "Magma Slime Sign Plate": "tconstruct:sign_head:0:ceaf4bc6",
  "Elemental Inscription Tool: Earth": "bloodmagic:ItemInscriptionTool:3",
  "Red Carpet": "minecraft:carpet:14",
  "Bone Axe Head": "tconstruct:axe_head:0:f18fe449",
  "Magenta Stained Clay": "minecraft:stained_hardened_clay:2",
  "Bed": "minecraft:bed:0",
  "Cobalt Pan": "tconstruct:pan_head:0:207823b8",
  "Firewood Hand Guard": "tconstruct:hand_guard:0:aa8d0aa8",
  "Cobblestone Slab": "minecraft:stone_slab:3",
  "Hand Guard Clay Cast": "tconstruct:clay_cast:0:d0c773d7",
  "Cactus Tool Rod": "tconstruct:tool_rod:0:3ea590f2",
  "Slime Hand Guard": "tconstruct:hand_guard:0:1424241f",
  "Booster": "rftools:booster:0",
  "Cactus Shard": "tconstruct:shard:0:3ea590f2",
  "Awkward Splash Potion": "minecraft:splash_potion:0:174fc869",
  "Lingering Potion of Water Breathing": "minecraft:lingering_potion:0:f56a775",
  "Seared Cobblestone": "tconstruct:seared:1",
  "Pink Carpet": "minecraft:carpet:6",
  "Prismarine Axe Head": "tconstruct:axe_head:0:5bbd0ef3",
  "Black Stained Glass Pane": "minecraft:stained_glass_pane:15",
  "Molten Gold": "fluid:gold",
  "Dark Oak Door": "minecraft:dark_oak_door:0",
  "Magenta Dye": "minecraft:dye:13",
  "Ardite Large Plate": "tconstruct:large_plate:0:f34653ac",
  "Sand": "minecraft:sand:0",
  "Firewood Large Sword Blade": "tconstruct:large_sword_blade:0:aa8d0aa8",
  "Machine Base": "rftools:machine_base:0",
  "Ardite Pickaxe Head": "tconstruct:pick_head:0:f34653ac",
  "Netherrack": "minecraft:netherrack:0",
  "Dark Oak Sapling": "minecraft:sapling:5",
  "Stone": "minecraft:stone:0",
  "Sigil of Suppression": "bloodmagic:ItemSigilSuppression:0",
  "Shield Template": "rftools:shield_template_block:3",
  "Ethereal Slate": "bloodmagic:ItemSlate:4",
  "Elemental Inscription Tool: Air": "bloodmagic:ItemInscriptionTool:4",
  "Splash Potion of Slowness": "minecraft:splash_potion:0:fe290b73",
  "Green Stained Clay": "minecraft:stained_hardened_clay:13",
  "Splash Potion of Strength": "minecraft:splash_potion:0:e37bb761",
  "Obsidian Hammer Head": "tconstruct:hammer_head:0:4df63d20",
  "Fermented Spider Eye": "minecraft:fermented_spider_eye:0",
  "Diamond Leggings": "minecraft:diamond_leggings:0",
  "Demon Crucible": "bloodmagic:BlockDemonCrucible:0",
  "Tripwire Hook": "minecraft:tripwire_hook:0",
  "Manyullyn Item Frame": "tconstruct:fancy_frame:4",
  "Shovel Head Clay Cast": "tconstruct:clay_cast:0:802428d0",
  "Iron Hammer Head": "tconstruct:hammer_head:0:fdacad4d",
  "Magma Slime Sharpening Kit": "tconstruct:sharpening_kit:0:ceaf4bc6",
  "Blue Stained Glass Pane": "minecraft:stained_glass_pane:11",
  "Slimy Grass": "tconstruct:slime_grass:10",
  "Obsidian Sword Blade": "tconstruct:sword_blade:0:4df63d20",
  "Lavawood": "tconstruct:firewood:0",
  "Netherrack Hammer Head": "tconstruct:hammer_head:0:20beaa74",
  "Bone Large Plate": "tconstruct:large_plate:0:f18fe449",
  "Cobalt Binding": "tconstruct:binding:0:207823b8",
  "Red Banner": "minecraft:banner:1",
  "Lava Bucket": "minecraft:lava_bucket:0",
  "Dark Oak Fence Gate": "minecraft:dark_oak_fence_gate:0",
  "Stick": "minecraft:stick:0",
  "Obsidian Hand Guard": "tconstruct:hand_guard:0:4df63d20",
  "Gravel": "minecraft:gravel:0",
  "Sunflower": "minecraft:double_plant:0",
  "Mundane Splash Potion": "minecraft:splash_potion:0:b90772f2",
  "Ardite Binding": "tconstruct:binding:0:f34653ac",
  "Red Tulip": "minecraft:red_flower:4",
  "Slime Tough Binding": "tconstruct:tough_binding:0:1424241f",
  "Spruce Wood Planks": "minecraft:planks:1",
  "Lingering Potion of Leaping": "minecraft:lingering_potion:0:bea1eb2",
  "Orange Tulip": "minecraft:red_flower:5",
  "Sign Plate Clay Cast": "tconstruct:clay_cast:0:df0eccb6",
  "Light Blue Carpet": "minecraft:carpet:3",
  "End Pan": "tconstruct:pan_head:0:ccc1936f",
  "Raw Mutton": "minecraft:mutton:0",
  "Cactus Green": "minecraft:dye:2",
  "Granite": "minecraft:stone:1",
  "Lime Carpet": "minecraft:carpet:5",
  "Pig Iron Sharpening Kit": "tconstruct:sharpening_kit:0:1d383047",
  "Peony": "minecraft:double_plant:5",
  "Peace Essence": "rftools:peace_essence:0",
  "Pig Iron Sword Blade": "tconstruct:sword_blade:0:1d383047",
  "End Binding": "tconstruct:binding:0:ccc1936f",
  "Slime Ball": "tconstruct:edible:4",
  "Firewood Binding": "tconstruct:binding:0:aa8d0aa8",
  "Living Chestplate": "bloodmagic:ItemLivingArmourChest:0",
  "Obsidian Tough Binding": "tconstruct:tough_binding:0:4df63d20",
  "Environmental Controller": "rftools:environmental_controller:0",
  "Golden Item Frame": "tconstruct:fancy_frame:5",
  "Arrow of Harming": "minecraft:tipped_arrow:0:997f14a6",
  "Space Chamber Card": "rftools:space_chamber_card:0",
  "Netherrack Sword Blade": "tconstruct:sword_blade:0:20beaa74",
  "Oak Door": "minecraft:wooden_door:0",
  "Diamond": "minecraft:diamond:0",
  "Flint Large Plate": "tconstruct:large_plate:0:ea5d31a",
  "Oak Wood Slab": "minecraft:wooden_slab:0",
  "Cauldron": "minecraft:cauldron:0",
  "Liquid Dirt": "fluid:dirt",
  "Lapis Lazuli Block": "minecraft:lapis_block:0",
  "Displacement Rune": "bloodmagic:BlockBloodRune:5",
  "Golden Leggings": "minecraft:golden_leggings:0",
  "Diorite": "minecraft:stone:3",
  "Seared Window": "tconstruct:seared_tank:2",
  "Glowstone Dust": "minecraft:glowstone_dust:0",
  "Demonic Slate": "bloodmagic:ItemSlate:3",
  "Wooden Shovel Head": "tconstruct:shovel_head:0:156619f2",
  "Iron Sword": "minecraft:iron_sword:0",
  "Pig Iron Hammer Head": "tconstruct:hammer_head:0:1d383047",
  "Cactus Large Plate": "tconstruct:large_plate:0:3ea590f2",
  "Polished Diorite": "minecraft:stone:4",
  "White Stained Glass Pane": "minecraft:stained_glass_pane:0",
  "Chest": "minecraft:chest:0",
  "Wooden Axe Head": "tconstruct:axe_head:0:156619f2",
  "Iron Boots": "minecraft:iron_boots:0",
  "Vines": "minecraft:vine:0",
  "Ardite Shard": "tconstruct:shard:0:f34653ac",
  "Mundane Potion": "minecraft:potion:0:b90772f2",
  "Gray Dye": "minecraft:dye:8",
  "End Crystal": "minecraft:end_crystal:0",
  "Lava Crystal": "bloodmagic:ItemLavaCrystal:0",
  "Thick Splash Potion": "minecraft:splash_potion:0:5bc2e955",
  "Brewing Stand": "minecraft:brewing_stand:0",
  "Gray Carpet": "minecraft:carpet:7",
  "Prismarine Hand Guard": "tconstruct:hand_guard:0:5bbd0ef3",
  "Molten Manyullyn": "fluid:manyullyn",
  "Worn Stone Brick Path": "bloodmagic:BlockPath:4",
  "Crafting Station": "tconstruct:tooltables:0",
  "TNT": "minecraft:tnt:0",
  "Brick Stairs": "minecraft:brick_stairs:0",
  "Minecart with TNT": "minecraft:tnt_minecart:0",
  "Magenta Banner": "minecraft:banner:13",
  "Tipped Arrow": "minecraft:tipped_arrow:0:174fc869",
  "Pig Iron Sign Plate": "tconstruct:sign_head:0:1d383047",
  "Cooked Rabbit": "minecraft:cooked_rabbit:0",
  "Ritual Stone": "bloodmagic:BlockRitualStone:0",
  "Sponge Tough Binding": "tconstruct:tough_binding:0:ea54e05f",
  "Binding Reagent": "bloodmagic:ItemComponent:8",
  "Stencil Table": "tconstruct:tooltables:1:6f9af3ab",
  "Eye of Ender": "minecraft:ender_eye:0",
  "Molten Knightslime": "fluid:knightslime",
  "Input Routing Node": "bloodmagic:BlockInputRoutingNode:0",
  "Green Slime Crystal": "tconstruct:materials:9",
  "Suppression Reagent": "bloodmagic:ItemComponent:9",
  "Cobalt Nugget": "tconstruct:nuggets:0",
  "Iron Large Sword Blade": "tconstruct:large_sword_blade:0:fdacad4d",
  "Jungle Door": "minecraft:jungle_door:0",
  "Jungle Wood Stairs": "minecraft:jungle_stairs:0",
  "Map": "minecraft:filled_map:0",
  "Bone Broad Axe Head": "tconstruct:broad_axe_head:0:f18fe449",
  "Ardite Sign Plate": "tconstruct:sign_head:0:f34653ac",
  "Demon Pylon": "bloodmagic:BlockDemonPylon:0",
  "Blank Rune": "bloodmagic:BlockBloodRune:0",
  "Orange Banner": "minecraft:banner:14",
  "Birch Fence": "minecraft:birch_fence:0",
  "Manyullyn Hand Guard": "tconstruct:hand_guard:0:7484c1bc",
  "Cactus Sign Plate": "tconstruct:sign_head:0:3ea590f2",
  "Hay Bale": "minecraft:hay_block:0",
  "Prismarine Tough Tool Rod": "tconstruct:tough_tool_rod:0:5bbd0ef3",
  "Cobalt Item Frame": "tconstruct:fancy_frame:2",
  "Advanced Powercell": "rftools:powercell_advanced:0",
  "Light Gray Stained Glass Pane": "minecraft:stained_glass_pane:8",
  "Flint Sharpening Kit": "tconstruct:sharpening_kit:0:ea5d31a",
  "End Excavator Head": "tconstruct:excavator_head:0:ccc1936f",
  "Knightslime Sword Blade": "tconstruct:sword_blade:0:eb40d90c",
  "Block of Coal": "minecraft:coal_block:0",
  "Sponge Hammer Head": "tconstruct:hammer_head:0:ea54e05f",
  "Golden Sword": "minecraft:golden_sword:0",
  "Destructive Will Crystal Cluster": "bloodmagic:BlockDemonCrystal:2",
  "Expander (Horizontal)": "tconstruct:materials:12",
  "Sacrificial Dagger": "bloodmagic:ItemSacrificialDagger:0",
  "Sharpening Kit Cast": "tconstruct:cast:0:e2749cc8",
  "Cobalt Large Plate": "tconstruct:large_plate:0:207823b8",
  "Magenta Stained Glass": "minecraft:stained_glass:2",
  "Netherrack Tool Rod": "tconstruct:tool_rod:0:20beaa74",
  "Knightslime Excavator Head": "tconstruct:excavator_head:0:eb40d90c",
  "Nether Star": "minecraft:nether_star:0",
  "Living Helmet": "bloodmagic:ItemLivingArmourHelmet:0",
  "Cobalt Hand Guard": "tconstruct:hand_guard:0:207823b8",
  "Iron Helmet": "minecraft:iron_helmet:0",
  "Bricks Slab": "minecraft:stone_slab:4",
  "Empty Map": "minecraft:map:0",
  "Lava Reagent": "bloodmagic:ItemComponent:1",
  "Air Sigil": "bloodmagic:ItemSigilAir:0",
  "Cobalt Ingot": "tconstruct:ingots:0",
  "Remote Storage Module": "rftools:storage_module:6",
  "Snow": "minecraft:snow:0",
  "Note Block": "minecraft:noteblock:0",
  "Stone Tool Rod": "tconstruct:tool_rod:0:cc51ef16",
  "Smooth Sandstone": "minecraft:sandstone:2",
  "Spruce Sapling": "minecraft:sapling:1",
  "Flint Large Sword Blade": "tconstruct:large_sword_blade:0:ea5d31a",
  "Pig Iron Tool Rod": "tconstruct:tool_rod:0:1d383047",
  "Prismarine Shard": "tconstruct:shard:0:5bbd0ef3",
  "Splash Potion of Water Breathing": "minecraft:splash_potion:0:f56a775",
  "Destination Analyzer": "rftools:destination_analyzer:0",
  "Rose Red": "minecraft:dye:1",
  "Molten Pigiron": "fluid:pigiron",
  "Smooth Red Sandstone": "minecraft:red_sandstone:2",
  "Charged Porter": "rftools:charged_porter:0",
  "Tool Rod Cast": "tconstruct:cast:0:6becbea2",
  "Broad Axe Head Clay Cast": "tconstruct:clay_cast:0:1d4334d0",
  "Glowball": "tconstruct:throwball:0",
  "Bone Tough Tool Rod": "tconstruct:tough_tool_rod:0:f18fe449",
  "Prismarine Pan": "tconstruct:pan_head:0:5bbd0ef3",
  "Magma Slime Broad Axe Head": "tconstruct:broad_axe_head:0:ceaf4bc6",
  "Ardite Hammer Head": "tconstruct:hammer_head:0:f34653ac",
  "Demon Will Crystal": "bloodmagic:ItemDemonCrystal:0",
  "Hammer Head Cast": "tconstruct:cast:0:b990094d",
  "Cactus Hammer Head": "tconstruct:hammer_head:0:3ea590f2",
  "Dark Oak Wood Planks": "minecraft:planks:5",
  "Leather Pants": "minecraft:leather_leggings:0",
  "Sequencer": "rftools:sequencer_block:0",
  "Enchantment Table": "minecraft:enchanting_table:0",
  "Demon Will Crystal Cluster": "bloodmagic:BlockDemonCrystal:0",
  "Iron Hoe": "minecraft:iron_hoe:0",
  "Cyan Wool": "minecraft:wool:9",
  "Magma Slime Wide Guard": "tconstruct:wide_guard:0:ceaf4bc6",
  "Sigil of the Green Grove": "bloodmagic:ItemSigilGreenGrove:0",
  "Beetroot Soup": "minecraft:beetroot_soup:0",
  "Speed Module": "rftools:speed_module:0",
  "Netherrack Binding": "tconstruct:binding:0:20beaa74",
  "Book and Quill": "minecraft:writable_book:0",
  "Azure Bluet": "minecraft:red_flower:3",
  "Bow": "minecraft:bow:0",
  "Manyullyn Shard": "tconstruct:shard:0:7484c1bc",
  "Bone Tough Binding": "tconstruct:tough_binding:0:f18fe449",
  "Slimesling": "tconstruct:slimesling:0",
  "Blue Banner": "minecraft:banner:4",
  "Cactus Pan": "tconstruct:pan_head:0:3ea590f2",
  "Blank Slate": "bloodmagic:ItemSlate:0",
  "Iron Large Plate": "tconstruct:large_plate:0:fdacad4d",
  "Oak Fence": "minecraft:fence:0",
  "Builder Block": "rftools:builder:0",
  "EFLN": "tconstruct:throwball:1",
  "Bone Large Sword Blade": "tconstruct:large_sword_blade:0:f18fe449",
  "Manyullyn Axe Head": "tconstruct:axe_head:0:7484c1bc",
  "Sponge Broad Axe Head": "tconstruct:broad_axe_head:0:ea54e05f",
  "Shape Card (Clearing Fortune Quarry)": "rftools:shape_card:7",
  "Golden Hoe": "minecraft:golden_hoe:0",
  "Nether Quartz Ore": "minecraft:quartz_ore:0",
  "Magma Cream": "minecraft:magma_cream:0",
  "Master Blood Orb": "bloodmagic:ItemBloodOrb:3",
  "Knightslime Sign Plate": "tconstruct:sign_head:0:eb40d90c",
  "Iron Wide Guard": "tconstruct:wide_guard:0:fdacad4d",
  "Shape Card (Fortune Quarry)": "rftools:shape_card:4",
  "Weighted Pressure Plate (Light)": "minecraft:light_weighted_pressure_plate:0",
  "Blood Letter\u0027s Pack": "bloodmagic:ItemPackSelfSacrifice:0",
  "Light Blue Stained Clay": "minecraft:stained_hardened_clay:3",
  "Magma Slime Shovel Head": "tconstruct:shovel_head:0:ceaf4bc6",
  "Slimy Magma Mud": "tconstruct:soil:5",
  "Ender Pearl": "minecraft:ender_pearl:0",
  "Golden Pickaxe": "minecraft:golden_pickaxe:0",
  "Ardite Tough Binding": "tconstruct:tough_binding:0:f34653ac",
  "Space Chamber Corner Block": "rftools:space_chamber:0",
  "Ritual Stone of Dusk": "bloodmagic:BlockRitualStone:5",
  "Nether Brick Fence": "minecraft:nether_brick_fence:0",
  "Knightslime Pan": "tconstruct:pan_head:0:eb40d90c",
  "Potion of Weakness": "minecraft:potion:0:98548baa",
  "Netherrack Large Plate": "tconstruct:large_plate:0:20beaa74",
  "Flint Broad Axe Head": "tconstruct:broad_axe_head:0:ea5d31a",
  "Bound Pickaxe": "bloodmagic:ItemBoundPickaxe:0",
  "Bone Hammer Head": "tconstruct:hammer_head:0:f18fe449",
  "Potion of Harming": "minecraft:potion:0:a53c0824",
  "Security Card": "rftools:security_card:0",
  "Steak": "minecraft:cooked_beef:0",
  "Expander (Vertical)": "tconstruct:materials:13",
  "Manyullyn Sword Blade": "tconstruct:sword_blade:0:7484c1bc",
  "NBT Item Filter": "bloodmagic:ItemRouterFilter:1",
  "Bucket of Life": "bloodmagic:ItemBucketEssence:0",
  "Flint Sword Blade": "tconstruct:sword_blade:0:ea5d31a",
  "Lingering Potion of Weakness": "minecraft:lingering_potion:0:f0126d2d",
  "Painting": "minecraft:painting:0",
  "Incense Altar": "bloodmagic:BlockIncenseAltar:0",
  "Purple Wool": "minecraft:wool:10",
  "Bookshelf": "minecraft:bookshelf:0",
  "Slime Sword Blade": "tconstruct:sword_blade:0:1424241f",
  "Netherrack Large Sword Blade": "tconstruct:large_sword_blade:0:20beaa74",
  "Obsidian Tool Rod": "tconstruct:tool_rod:0:4df63d20",
  "Peaceful Module": "rftools:peaceful_module:0",
  "Magenta Carpet": "minecraft:carpet:2",
  "Gray Banner": "minecraft:banner:8",
  "Paper": "minecraft:paper:0",
  "Magnetism Reagent": "bloodmagic:ItemComponent:12",
  "Potion of Invisibility": "minecraft:potion:0:1ba7f9d2",
  "Elemental Inscription Tool: Dawn": "bloodmagic:ItemInscriptionTool:6",
  "Slime Shard": "tconstruct:shard:0:1424241f",
  "Sigil of Elemental Affinity": "bloodmagic:ItemSigilElementalAffinity:0",
  "Stone Large Plate": "tconstruct:large_plate:0:cc51ef16",
  "RF Network Monitor": "rftools:network_monitor:0",
  "Paper Broad Axe Head": "tconstruct:broad_axe_head:0:d3d5a7d",
  "Bone Excavator Head": "tconstruct:excavator_head:0:f18fe449",
  "Raw Rabbit": "minecraft:rabbit:0",
  "Sigil of the Phantom Bridge": "bloodmagic:ItemSigilPhantomBridge:0",
  "Bone Shard": "tconstruct:shard:0:f18fe449",
  "Blood": "fluid:blood",
  "Paper Pickaxe Head": "tconstruct:pick_head:0:d3d5a7d",
  "Molten Obsidian": "fluid:obsidian",
  "Altar Maker": "bloodmagic:ItemAltarMaker:0",
  "Magma Slime Tough Binding": "tconstruct:tough_binding:0:ceaf4bc6",
  "Black Carpet": "minecraft:carpet:15",
  "Leather Cap": "minecraft:leather_helmet:0",
  "Light Gray Wool": "minecraft:wool:8",
  "Faucet": "tconstruct:faucet:0",
  "Manyullyn Large Plate": "tconstruct:large_plate:0:7484c1bc",
  "Spawner": "rftools:spawner:0",
  "Coagulated Blood": "tconstruct:edible:3",
  "Sign Plate Cast": "tconstruct:cast:0:df0eccb6",
  "Powercell": "rftools:powercell:0",
  "Storage Scanner": "rftools:storage_scanner:0",
  "Vengeful Will Crystal": "bloodmagic:ItemDemonCrystal:3",
  "Cookie": "minecraft:cookie:0",
  "Magenta Wool": "minecraft:wool:2",
  "Stone Rod": "tconstruct:stone_stick:0",
  "Demonic Teleposition Focus": "bloodmagic:ItemTelepositionFocus:3",
  "Knightslime Hand Guard": "tconstruct:hand_guard:0:eb40d90c",
  "Cactus Wide Guard": "tconstruct:wide_guard:0:3ea590f2",
  "Haste Reagent": "bloodmagic:ItemComponent:13",
  "Aluminium Brass Item Frame": "tconstruct:fancy_frame:1",
  "Output Routing Node": "bloodmagic:BlockOutputRoutingNode:0",
  "End Pickaxe Head": "tconstruct:pick_head:0:ccc1936f",
  "Wooden Large Sword Blade": "tconstruct:large_sword_blade:0:156619f2",
  "Beacon": "minecraft:beacon:0",
  "Ritual Stone of Earth": "bloodmagic:BlockRitualStone:3",
  "Blaze Powder": "minecraft:blaze_powder:0",
  "Yellow Banner": "minecraft:banner:11",
  "Wheat": "minecraft:wheat:0",
  "Nether Quartz": "minecraft:quartz:0",
  "Paper Sharpening Kit": "tconstruct:sharpening_kit:0:d3d5a7d",
  "Congealed Blood Slime Block": "tconstruct:slime_congealed:3",
  "Pig Iron Binding": "tconstruct:binding:0:1d383047",
  "Light Blue Stained Glass": "minecraft:stained_glass:3",
  "Awkward Potion": "minecraft:potion:0:174fc869",
  "Block of Knightslime": "tconstruct:metal:3",
  "Machine Frame": "rftools:machine_frame:0",
  "Firewood Axe Head": "tconstruct:axe_head:0:aa8d0aa8",
  "Nether Brick": "minecraft:netherbrick:0",
  "Cake": "minecraft:cake:0",
  "Acacia Wood Planks": "minecraft:planks:4",
  "Wooden Path": "bloodmagic:BlockPath:0",
  "Obsidian Shard": "tconstruct:shard:0:4df63d20",
  "Purple Slime Block": "tconstruct:slime:2",
  "Manyullyn Tough Binding": "tconstruct:tough_binding:0:7484c1bc",
  "Weakness Module": "rftools:weakness_module:0",
  "Blindness Module": "rftools:blindness_module:0",
  "Potion of Swiftness": "minecraft:potion:0:e2dae2e0",
  "Teleposer": "bloodmagic:BlockTeleposer:0",
  "Firewood Hammer Head": "tconstruct:hammer_head:0:aa8d0aa8",
  "Oak Boat": "minecraft:boat:0",
  "Silky Jewel": "tconstruct:materials:16",
  "Andesite": "minecraft:stone:5",
  "Cracked Stone Bricks": "minecraft:stonebrick:2",
  "Sponge Sharpening Kit": "tconstruct:sharpening_kit:0:ea54e05f",
  "Tough Binding Cast": "tconstruct:cast:0:f93bf55",
  "Red Sandstone Slab": "minecraft:stone_slab2:0",
  "Item Frame": "minecraft:item_frame:0",
  "Stone Torch": "tconstruct:stone_torch:0",
  "Lingering Potion of Fire Resistance": "minecraft:lingering_potion:0:2bd7b21a",
  "Manyullyn Tough Tool Rod": "tconstruct:tough_tool_rod:0:7484c1bc",
  "Pink Stained Clay": "minecraft:stained_hardened_clay:6",
  "Cobalt Sword Blade": "tconstruct:sword_blade:0:207823b8",
  "Red Stained Clay": "minecraft:stained_hardened_clay:14",
  "Weak Blood Orb": "bloodmagic:ItemBloodOrb:0",
  "Mushroom": "minecraft:brown_mushroom:0",
  "Acceleration Rune": "bloodmagic:BlockBloodRune:9",
  "Wooden Shard": "tconstruct:shard:0:156619f2",
  "Ice": "minecraft:ice:0",
  "Severance Reagent": "bloodmagic:ItemComponent:16",
  "Firewood Sword Blade": "tconstruct:sword_blade:0:aa8d0aa8",
  "Splash Water Bottle": "minecraft:splash_potion:0:ef1fb44f",
  "Flight Module": "rftools:flight_module:0",
  "Pigiron Ingot": "tconstruct:ingots:4",
  "Ritual Tinkerer": "bloodmagic:ItemRitualReader:0",
  "Netherrack Broad Axe Head": "tconstruct:broad_axe_head:0:20beaa74",
  "Cyan Stained Glass Pane": "minecraft:stained_glass_pane:9",
  "Prismarine Large Sword Blade": "tconstruct:large_sword_blade:0:5bbd0ef3",
  "Precise Item Filter": "bloodmagic:ItemRouterFilter:0",
  "Jungle Fence": "minecraft:jungle_fence:0",
  "Flint Binding": "tconstruct:binding:0:ea5d31a",
  "Wooden Hand Guard": "tconstruct:hand_guard:0:156619f2",
  "Broad Axe Head Cast": "tconstruct:cast:0:1d4334d0",
  "Netherrack Pickaxe Head": "tconstruct:pick_head:0:20beaa74",
  "Shape Card": "rftools:shape_card:0",
  "Cobalt Hammer Head": "tconstruct:hammer_head:0:207823b8",
  "Pan Clay Cast": "tconstruct:clay_cast:0:7614c7c4",
  "Lime Stained Glass Pane": "minecraft:stained_glass_pane:5",
  "Mining Reagent": "bloodmagic:ItemComponent:3",
  "Potato": "minecraft:potato:0",
  "Teleposition Sigil": "bloodmagic:ItemSigilTeleposition:0",
  "Wooden Pickaxe": "minecraft:wooden_pickaxe:0",
  "White Tulip": "minecraft:red_flower:6",
  "Cactus Broad Axe Head": "tconstruct:broad_axe_head:0:3ea590f2",
  "Magma Slime Axe Head": "tconstruct:axe_head:0:ceaf4bc6",
  "White Stained Clay": "minecraft:stained_hardened_clay:0",
  "Pumpkin Pie": "minecraft:pumpkin_pie:0",
  "Clay": "minecraft:clay_ball:0",
  "Smart Wrench": "rftools:smartwrench:0",
  "Cactus Sharpening Kit": "tconstruct:sharpening_kit:0:3ea590f2",
  "Light Gray Carpet": "minecraft:carpet:8",
  "Magma Slime Excavator Head": "tconstruct:excavator_head:0:ceaf4bc6",
  "Ghast Tear": "minecraft:ghast_tear:0",
  "Pig Iron Tough Binding": "tconstruct:tough_binding:0:1d383047",
  "Cobalt Ore": "tconstruct:ore:0",
  "Netherrack Sign Plate": "tconstruct:sign_head:0:20beaa74",
  "Obsidian": "minecraft:obsidian:0",
  "Seared Gauge": "tconstruct:seared_tank:1",
  "Cactus Binding": "tconstruct:binding:0:3ea590f2",
  "Allium": "minecraft:red_flower:2",
  "Sigil of the Fast Miner": "bloodmagic:ItemSigilFastMiner:0",
  "Cobalt Excavator Head": "tconstruct:excavator_head:0:207823b8",
  "Birch Wood Planks": "minecraft:planks:2",
  "Pink Dye": "minecraft:dye:9",
  "Stone Hand Guard": "tconstruct:hand_guard:0:cc51ef16",
  "Raw Salmon": "minecraft:fish:1",
  "Pig Iron Large Sword Blade": "tconstruct:large_sword_blade:0:1d383047",
  "Sponge Wide Guard": "tconstruct:wide_guard:0:ea54e05f",
  "Stone Brick Stairs": "minecraft:stone_brick_stairs:0",
  "Rune of Capacity": "bloodmagic:BlockBloodRune:6",
  "Sponge Binding": "tconstruct:binding:0:ea54e05f",
  "Paper Excavator Head": "tconstruct:excavator_head:0:d3d5a7d",
  "Diamond Axe": "minecraft:diamond_axe:0",
  "Machine Information Module": "rftools:machineinformation_module:0",
  "Shape Card (Clearing Silk Quarry)": "rftools:shape_card:6",
  "Demon Crystallizer": "bloodmagic:BlockDemonCrystallizer:0",
  "Rabbit\u0027s Foot": "minecraft:rabbit_foot:0",
  "Iron Ore": "minecraft:iron_ore:0",
  "Diamond Shovel": "minecraft:diamond_shovel:0",
  "Birch Fence Gate": "minecraft:birch_fence_gate:0",
  "Lime Stained Glass": "minecraft:stained_glass:5",
  "Splash Potion of Healing": "minecraft:splash_potion:0:bfc1f3b0",
  "Bone Sharpening Kit": "tconstruct:sharpening_kit:0:f18fe449",
  "Purple Banner": "minecraft:banner:5",
  "Orange Stained Clay": "minecraft:stained_hardened_clay:1",
  "Light Blue Dye": "minecraft:dye:12",
  "Splash Potion of Night Vision": "minecraft:splash_potion:0:27447fca",
  "Elevator": "rftools:elevator:0",
  "Rune of Augmented Capacity": "bloodmagic:BlockBloodRune:7",
  "Regeneration Plus Module": "rftools:regenerationplus_module:0",
  "Green Wool": "minecraft:wool:13",
  "Paper Pan": "tconstruct:pan_head:0:d3d5a7d",
  "Tool Station": "tconstruct:tooltables:3",
  "Fluid Module": "rftools:fluid_module:0",
  "Knightslime Tough Binding": "tconstruct:tough_binding:0:eb40d90c",
  "Flint Pickaxe Head": "tconstruct:pick_head:0:ea5d31a",
  "Iron Shard": "tconstruct:shard:0:fdacad4d",
  "Knightslime Binding": "tconstruct:binding:0:eb40d90c",
  "Iron Tough Binding": "tconstruct:tough_binding:0:fdacad4d",
  "Sponge Pan": "tconstruct:pan_head:0:ea54e05f",
  "Cracked Seared Bricks": "tconstruct:seared:4",
  "Blue Carpet": "minecraft:carpet:11",
  "Manyullyn Ingot": "tconstruct:ingots:2",
  "Splash Potion of Leaping": "minecraft:splash_potion:0:21dbbc95",
  "Ore Dictionary Item Filter": "bloodmagic:ItemRouterFilter:3",
  "Tool Rod Clay Cast": "tconstruct:clay_cast:0:6becbea2",
  "Blood Slime Block": "tconstruct:slime:3",
  "Binding Clay Cast": "tconstruct:clay_cast:0:7a078199",
  "Syringe": "rftools:syringe:0:645d0b5d",
  "Sponge": "minecraft:sponge:0",
  "Wooden Rail": "tconstruct:wood_rail:0",
  "Chiseled Stone Bricks": "minecraft:stonebrick:3",
  "Bone": "minecraft:bone:0",
  "Axe Head Clay Cast": "tconstruct:clay_cast:0:d1028c33",
  "Magma Slime Sword Blade": "tconstruct:sword_blade:0:ceaf4bc6",
  "Paper Wide Guard": "tconstruct:wide_guard:0:d3d5a7d",
  "Paper Shard": "tconstruct:shard:0:d3d5a7d",
  "Moss Stone": "minecraft:mossy_cobblestone:0",
  "Acacia Fence": "minecraft:acacia_fence:0",
  "Slime Large Plate": "tconstruct:large_plate:0:1424241f",
  "Congealed Magma Slime Block": "tconstruct:slime_congealed:4",
  "Arcane Ashes": "bloodmagic:ItemArcaneAshes:0",
  "Obsidian Broad Axe Head": "tconstruct:broad_axe_head:0:4df63d20",
  "Block of Ardite": "tconstruct:metal:1",
  "Brown Stained Clay": "minecraft:stained_hardened_clay:12",
  "Torch": "minecraft:torch:0",
  "Manyullyn Large Sword Blade": "tconstruct:large_sword_blade:0:7484c1bc",
  "Cobalt Sign Plate": "tconstruct:sign_head:0:207823b8",
  "Book": "minecraft:book:0",
  "Pig Iron Tough Tool Rod": "tconstruct:tough_tool_rod:0:1d383047",
  "Obsidian Sharpening Kit": "tconstruct:sharpening_kit:0:4df63d20",
  "Spectral Arrow": "minecraft:spectral_arrow:0",
  "Pig Iron Pan": "tconstruct:pan_head:0:1d383047",
  "Dimensional Shard": "rftools:dimensional_shard:0",
  "Matter Booster": "rftools:matter_booster:0",
  "Dark Prismarine": "minecraft:prismarine:2",
  "Purple Stained Glass Pane": "minecraft:stained_glass_pane:10",
  "Arrow of Swiftness": "minecraft:tipped_arrow:0:328e8805",
  "Dandelion": "minecraft:yellow_flower:0",
  "Acacia Door": "minecraft:acacia_door:0",
  "Quartz Stairs": "minecraft:quartz_stairs:0",
  "Large Plate Cast": "tconstruct:cast:0:76924066",
  "Lava": "fluid:lava",
  "Blood Altar": "bloodmagic:BlockAltar:0",
  "Sponge Pickaxe Head": "tconstruct:pick_head:0:ea54e05f",
  "Flint Tough Binding": "tconstruct:tough_binding:0:ea5d31a",
  "Void Sigil": "bloodmagic:ItemSigilVoid:0",
  "Purple Dye": "minecraft:dye:5",
  "Shape Card (Clearing Quarry)": "rftools:shape_card:5",
  "Ardite Ingot": "tconstruct:ingots:1",
  "Compass": "minecraft:compass:0",
  "Brown Wool": "minecraft:wool:12",
  "item.infused_diamond.name": "rftools:infused_diamond:0",
  "Stone Ladder": "tconstruct:stone_ladder:0",
  "Snowball": "minecraft:snowball:0",
  "Pink Wool": "minecraft:wool:6",
  "Iron Door": "minecraft:iron_door:0",
  "Lever": "minecraft:lever:0",
  "Orange Carpet": "minecraft:carpet:1",
  "Acacia Wood Slab": "minecraft:wooden_slab:4",
  "Blue Stained Clay": "minecraft:stained_hardened_clay:11",
  "Arrow of Water Breathing": "minecraft:tipped_arrow:0:f56a775",
  "Netherrack Wide Guard": "tconstruct:wide_guard:0:20beaa74",
  "Block of Cobalt": "tconstruct:metal:0",
  "Lesser Tartaric Gem": "bloodmagic:ItemSoulGem:1",
  "Cactus Large Sword Blade": "tconstruct:large_sword_blade:0:3ea590f2",
  "Stone Pan": "tconstruct:pan_head:0:cc51ef16",
  "Dispenser": "minecraft:dispenser:0",
  "Flint Sign Plate": "tconstruct:sign_head:0:ea5d31a",
  "Slime Wide Guard": "tconstruct:wide_guard:0:1424241f",
  "Bone Binding": "tconstruct:binding:0:f18fe449",
  "Knightslime Axe Head": "tconstruct:axe_head:0:eb40d90c",
  "Nether Brick Stairs": "minecraft:nether_brick_stairs:0",
  "Common Tartaric Gem": "bloodmagic:ItemSoulGem:2:f62",
  "Knightslime Hammer Head": "tconstruct:hammer_head:0:eb40d90c",
  "Stone Shovel": "minecraft:stone_shovel:0",
  "Liquid Purple Slime": "fluid:purpleslime",
  "Cactus Tough Binding": "tconstruct:tough_binding:0:3ea590f2",
  "Green Stained Glass Pane": "minecraft:stained_glass_pane:13",
  "Magma Slime Crystal": "tconstruct:materials:11",
  "Ardite Excavator Head": "tconstruct:excavator_head:0:f34653ac",
  "Hellfire Forge": "bloodmagic:BlockSoulForge:0",
  "Knightslime Large Plate": "tconstruct:large_plate:0:eb40d90c",
  "Matter Receiver": "rftools:matter_receiver:0",
  "Redstone Transmitter": "rftools:redstone_transmitter_block:0",
  "Bone Shovel Head": "tconstruct:shovel_head:0:f18fe449",
  "Part Builder": "tconstruct:tooltables:2:5fcc45d3",
  "Stone Tough Tool Rod": "tconstruct:tough_tool_rod:0:cc51ef16",
  "Flint Pan": "tconstruct:pan_head:0:ea5d31a",
  "Spruce Wood Stairs": "minecraft:spruce_stairs:0",
  "Prismarine Sword Blade": "tconstruct:sword_blade:0:5bbd0ef3",
  "Dark Oak Wood": "minecraft:log2:1",
  "Light Blue Stained Glass Pane": "minecraft:stained_glass_pane:3",
  "Ardite Sword Blade": "tconstruct:sword_blade:0:f34653ac",
  "Ladder": "minecraft:ladder:0",
  "Birch Sapling": "minecraft:sapling:2",
  "Obsidian Large Sword Blade": "tconstruct:large_sword_blade:0:4df63d20",
  "Yellow Stained Glass": "minecraft:stained_glass:4",
  "End Sword Blade": "tconstruct:sword_blade:0:ccc1936f",
  "Stone Tough Binding": "tconstruct:tough_binding:0:cc51ef16",
  "Brown Carpet": "minecraft:carpet:12",
  "Wooden Tool Rod": "tconstruct:tool_rod:0:156619f2",
  "Cyan Carpet": "minecraft:carpet:9",
  "Bound Blade": "bloodmagic:ItemBoundSword:0",
  "Space Chamber Controller Block": "rftools:space_chamber_controller:0",
  "Speed Plus Module": "rftools:speedplus_module:0",
  "Aluminum Brass Nugget": "tconstruct:nuggets:5",
  "Sponge Sign Plate": "tconstruct:sign_head:0:ea54e05f",
  "Block of Manyullyn": "tconstruct:metal:2",
  "Netherrack Excavator Head": "tconstruct:excavator_head:0:20beaa74",
  "Rail": "minecraft:rail:0",
  "Ardite Sharpening Kit": "tconstruct:sharpening_kit:0:f34653ac",
  "Sentient Bow": "bloodmagic:ItemSentientBow:0",
  "Gem Cast": "tconstruct:cast_custom:2",
  "Lingering Potion of Luck": "minecraft:lingering_potion:0:615e640f",
  "Ardite Nugget": "tconstruct:nuggets:1",
  "Ardite Broad Axe Head": "tconstruct:broad_axe_head:0:f34653ac",
  "Red Stained Glass Pane": "minecraft:stained_glass_pane:14",
  "Slime Tool Rod": "tconstruct:tool_rod:0:1424241f",
  "Activator Rail": "minecraft:activator_rail:0",
  "Wooden Binding": "tconstruct:binding:0:156619f2",
  "Consecrated Soil": "tconstruct:soil:4",
  "Iron Chestplate": "minecraft:iron_chestplate:0",
  "Sponge Shovel Head": "tconstruct:shovel_head:0:ea54e05f",
  "Cobblestone Wall": "minecraft:cobblestone_wall:0",
  "Ender Chest": "minecraft:ender_chest:0",
  "Light Blue Banner": "minecraft:banner:12",
  "Cobalt Broad Axe Head": "tconstruct:broad_axe_head:0:207823b8",
  "Spruce Wood": "minecraft:log:1",
  "Cactus Excavator Head": "tconstruct:excavator_head:0:3ea590f2",
  "Green Carpet": "minecraft:carpet:13",
  "Destructive Will Crystal": "bloodmagic:ItemDemonCrystal:2",
  "Sword Blade Cast": "tconstruct:cast:0:ed0275aa",
  "Melon Seeds": "minecraft:melon_seeds:0",
  "Cobalt Sharpening Kit": "tconstruct:sharpening_kit:0:207823b8",
  "Arrow of Splashing": "minecraft:tipped_arrow:0:ef1fb44f",
  "Dandelion Yellow": "minecraft:dye:11",
  "Chiseled Sandstone": "minecraft:sandstone:1",
  "Baked Potato": "minecraft:baked_potato:0",
  "Netherrack Sharpening Kit": "tconstruct:sharpening_kit:0:20beaa74",
  "Bone Hand Guard": "tconstruct:hand_guard:0:f18fe449",
  "Screen": "rftools:screen:0",
  "Brown Stained Glass": "minecraft:stained_glass:12",
  "Netherrack Shovel Head": "tconstruct:shovel_head:0:20beaa74",
  "Yellow Wool": "minecraft:wool:4",
  "Spider Eye": "minecraft:spider_eye:0",
  "Screen Controller": "rftools:screen_controller:0",
  "Cobalt Large Sword Blade": "tconstruct:large_sword_blade:0:207823b8",
  "Bloodstone Brick": "bloodmagic:BlockBloodStoneBrick:1",
  "Matter Beamer": "rftools:matter_beamer:0",
  "Golden Helmet": "minecraft:golden_helmet:0",
  "Emerald": "minecraft:emerald:0",
  "Manyullyn Tool Rod": "tconstruct:tool_rod:0:7484c1bc",
  "Living Armour Training Bracelet": "bloodmagic:ItemUpgradeTrainer:0",
  "Seared Brick": "tconstruct:materials:0",
  "Firewood Pickaxe Head": "tconstruct:pick_head:0:aa8d0aa8",
  "Black Wool": "minecraft:wool:15",
  "Slime Hammer Head": "tconstruct:hammer_head:0:1424241f",
  "Archmage Blood Orb": "bloodmagic:ItemBloodOrb:4",
  "Egg": "minecraft:egg:0",
  "Redstone Repeater": "minecraft:repeater:0",
  "Magma Slime Sapling": "tconstruct:slime_sapling:2",
  "Flint Hammer Head": "tconstruct:hammer_head:0:ea5d31a",
  "Golden Chestplate": "minecraft:golden_chestplate:0",
  "Rudimentary Snare": "bloodmagic:ItemSoulSnare:0",
  "Binding Cast": "tconstruct:cast:0:7a078199",
  "Mossy Cobblestone Wall": "minecraft:cobblestone_wall:1",
  "Birch Wood": "minecraft:log:2",
  "Fancy Item Frame": "tconstruct:fancy_frame:0",
  "Magma Slime Pickaxe Head": "tconstruct:pick_head:0:ceaf4bc6",
  "Diamond Hoe": "minecraft:diamond_hoe:0",
  "Slimeball": "minecraft:slime_ball:0",
  "Bound Shovel": "bloodmagic:ItemBoundShovel:0"
}